keras_visualizer/__init__.py
keras_visualizer-3.2.0.dist-info/LICENSE
keras_visualizer-3.2.0.dist-info/METADATA
keras_visualizer-3.2.0.dist-info/WHEEL
keras_visualizer-3.2.0.dist-info/top_level.txt
keras_visualizer-3.2.0.dist-info/RECORD
