Metadata-Version: 2.1
Name: keras-visualizer
Version: 3.2.0
Summary: A Keras Model Visualizer
Home-page: https://github.com/lordmahyar/keras-visualizer
Author: Mahyar Amiri
Author-email: mmaahhyyaarr@gmail.com
License: MIT
Classifier: Programming Language :: Python :: 3
Classifier: License :: OSI Approved :: MIT License
Classifier: Operating System :: OS Independent
Requires-Python: >=3.6
License-File: LICENSE
Requires-Dist: graphviz
